setup.cfg
setup.py
emantools/__init__.py
emantools/countdown.py
emantools/create_daemon.py
emantools/daemon.py
emantools/endless-countdown.py
emantools.egg-info/PKG-INFO
emantools.egg-info/SOURCES.txt
emantools.egg-info/dependency_links.txt
emantools.egg-info/entry_points.txt
emantools.egg-info/not-zip-safe
emantools.egg-info/paster_plugins.txt
emantools.egg-info/top_level.txt