Metadata-Version: 1.0
Name: emantools
Version: 0.0dev-r12
Summary: Eman Tools
Home-page: http://eman-misc.googlecode.com/
Author: Emanuel G. Calso
Author-email: bloodpet@gmail.com
License: Python License
Keywords: Utilities Tools
Platform: UNKNOWN
